MANIFEST.in
README.rst
setup.py
daa/__init__.py
daa/admin.py
django_admin_auto.egg-info/PKG-INFO
django_admin_auto.egg-info/SOURCES.txt
django_admin_auto.egg-info/dependency_links.txt
django_admin_auto.egg-info/requires.txt
django_admin_auto.egg-info/top_level.txt