Metadata-Version: 1.1
Name: django-admin-auto
Version: 0.1.1
Summary: To automate the Django Admin displaying.
Home-page: https://github.com/excelwang/django-admin-auto
Author: Excel Wang
Author-email: wanghj@cnic.com
License: Apache-2.0 Licence
Keywords: pip,django,admin
Platform: UNKNOWN
Classifier: Programming Language :: Python :: 3
Classifier: Operating System :: OS Independent
